admin_views/__init__.py
admin_views/admin.py
admin_views/compat.py
admin_views/conf.py
admin_views/models.py
admin_views/tests.py
admin_views/static/admin_views/icons/link.png
admin_views/static/admin_views/icons/view.png
admin_views/templates/admin/index.html
django_admin_views-1.0.3.dist-info/AUTHORS.txt
django_admin_views-1.0.3.dist-info/LICENSE
django_admin_views-1.0.3.dist-info/METADATA
django_admin_views-1.0.3.dist-info/WHEEL
django_admin_views-1.0.3.dist-info/top_level.txt
django_admin_views-1.0.3.dist-info/RECORD
