Metadata-Version: 2.1
Name: django-admin-views
Version: 1.0.3
Summary: django-admin-views is a simple way to add custom admin views and direct URLs to the Django admin
Author-email: Hugo Defrance <defrance.hugo@gmail.com>
License: Copyright (c) Hugo Defrance and individual contributors.
Project-URL: Homepage, https://github.com/koleror/django-admin-views
Keywords: django,admin
Classifier: Environment :: Web Environment
Classifier: Intended Audience :: Developers
Classifier: License :: OSI Approved :: BSD License
Classifier: Operating System :: OS Independent
Classifier: Programming Language :: Python
Classifier: Framework :: Django
Requires-Python: >=3.9
License-File: LICENSE
License-File: AUTHORS.txt
Requires-Dist: django (>=3.2)
Provides-Extra: dev
Requires-Dist: black ; extra == 'dev'
Requires-Dist: bumpver ; extra == 'dev'
Requires-Dist: isort ; extra == 'dev'
